crontabs/__init__.py
crontabs/crontabs.py
crontabs/processes.py
crontabs/version.py
crontabs/tests/__init__.py
crontabs/tests/test_all.py
crontabs-0.2.2.dist-info/LICENSE
crontabs-0.2.2.dist-info/METADATA
crontabs-0.2.2.dist-info/WHEEL
crontabs-0.2.2.dist-info/top_level.txt
crontabs-0.2.2.dist-info/RECORD
